tournament/__init__.py
tournament/core/enum.py
tournament/core/models.py
tournament/csv/cleaner.py
tournament/csv/csv.py
pytournament-0.1.0.dist-info/METADATA
pytournament-0.1.0.dist-info/WHEEL
pytournament-0.1.0.dist-info/entry_points.txt
pytournament-0.1.0.dist-info/RECORD
